ticklist/__init__.py
ticklist/annotation_iterators.py
ticklist/field_data.py
ticklist/field_widgets.py
ticklist/form.py
ticklist/py.typed
ticklist/tick_annotations.py
ticklist/types.py
ticklist-0.9.0.dist-info/METADATA
ticklist-0.9.0.dist-info/WHEEL
ticklist-0.9.0.dist-info/licenses/LICENSE
ticklist-0.9.0.dist-info/RECORD
