Metadata-Version: 2.4
Name: ticklist
Version: 0.9.0
Summary: Create textual forms based on Pydantic models.
Project-URL: Repository, https://github.com/sander76/clipstick
License-File: LICENSE
Keywords: cli,forms,pydantic,textual
Classifier: Programming Language :: Python :: 3 :: Only
Classifier: Programming Language :: Python :: 3.11
Classifier: Programming Language :: Python :: 3.12
Classifier: Programming Language :: Python :: 3.13
Requires-Python: >=3.11
Requires-Dist: pydantic>=2.10.2
Requires-Dist: textual>=1
